{
  "_class": "shapePath",
  "booleanOperation": -1,
  "clippingMaskMode": 0,
  "do_objectID": "442F9C36-BEED-409F-A556-68C03B5EC69A",
  "edited": true,
  "exportOptions": {
    "_class": "exportOptions",
    "exportFormats": [
    ],
    "includedLayerIds": [
    ],
    "layerOptions": 0,
    "shouldTrim": false
  },
  "frame": {
    "_class": "rect",
    "constrainProportions": false,
    "height": 46.63932101599275,
    "width": 48.09357583594884,
    "x": 0.00005522407504621185,
    "y": -1.77635683940025e-15
  },
  "hasClippingMask": false,
  "isClosed": true,
  "isFixedToViewport": false,
  "isFlippedHorizontal": false,
  "isFlippedVertical": false,
  "isLocked": false,
  "isVisible": true,
  "layerListExpandedType": 0,
  "name": "Path",
  "nameIsFixed": false,
  "pointRadiusBehaviour": 1,
  "points": [
    {
      "_class": "curvePoint",
      "cornerRadius": 0,
      "curveFrom": "{0.91540992390683296, 0.16096396619998365}",
      "curveMode": 4,
      "curveTo": "{1.0074122455775103, 0.24732746518783899}",
      "hasCurveFrom": true,
      "hasCurveTo": true,
      "point": "{0.92611240600356515, 0.17056820021542635}"
    },
    {
      "_class": "curvePoint",
      "cornerRadius": 0,
      "curveFrom": "{0.88030083178267315, 0.10774518113992936}",
      "curveMode": 4,
      "curveTo": "{0.90385347942497896, 0.15242121102626352}",
      "hasCurveFrom": true,
      "hasCurveTo": true,
      "point": "{0.8915963615808673, 0.14505324900951272}"
    },
    {
      "_class": "curvePoint",
      "cornerRadius": 0,
      "curveFrom": "{0.82031007090880381, 0.021193037888955206}",
      "curveMode": 4,
      "curveTo": "{0.86192410738460667, 0.073125488062621688}",
      "hasCurveFrom": true,
      "hasCurveTo": true,
      "point": "{0.8375350871838706, 0.043207855540529451}"
    },
    {
      "_class": "curvePoint",
      "cornerRadius": 0,
      "curveFrom": "{0.73005285953623456, -0.001821557176426347}",
      "curveMode": 4,
      "curveTo": "{0.79620172667107336, 0.0060344625864045152}",
      "hasCurveFrom": true,
      "hasCurveTo": true,
      "point": "{0.76933471025227473, 0.00032558460622076366}"
    },
    {
      "_class": "curvePoint",
      "cornerRadius": 0,
      "curveFrom": "{0.6039476855255399, 0.050386646285048166}",
      "curveMode": 4,
      "curveTo": "{0.69091082583922758, 0.0066797054650439064}",
      "hasCurveFrom": true,
      "hasCurveTo": true,
      "point": "{0.65580603401858151, 0.024982890393448288}"
    },
    {
      "_class": "curvePoint",
      "cornerRadius": 0,
      "curveFrom": "{0.45390796694364388, 0.11224831174476625}",
      "curveMode": 4,
      "curveTo": "{0.55342072877851511, 0.078584940228705713}",
      "hasCurveFrom": true,
      "hasCurveTo": true,
      "point": "{0.5044344657069908, 0.10946096413403616}"
    },
    {
      "_class": "curvePoint",
      "cornerRadius": 0,
      "curveFrom": "{0.32088634909066144, 0.12625589963605077}",
      "curveMode": 4,
      "curveTo": "{0.40442110807254683, 0.12082476593162797}",
      "hasCurveFrom": true,
      "hasCurveTo": true,
      "point": "{0.35389460930919991, 0.12597063844374501}"
    },
    {
      "_class": "curvePoint",
      "cornerRadius": 0,
      "curveFrom": "{0.2599602364850549, 0.17336700634831739}",
      "curveMode": 4,
      "curveTo": "{0.28936233623341878, 0.14015436198003459}",
      "hasCurveFrom": true,
      "hasCurveTo": true,
      "point": "{0.26635693038175562, 0.16456468228462318}"
    },
    {
      "_class": "curvePoint",
      "cornerRadius": 0,
      "curveFrom": "{0.25762395528685594, 0.20122902393345712}",
      "curveMode": 4,
      "curveTo": "{0.25685927326804636, 0.18425425674346921}",
      "hasCurveFrom": true,
      "hasCurveTo": true,
      "point": "{0.25762395528685594, 0.19522550600265387}"
    },
    {
      "_class": "curvePoint",
      "cornerRadius": 0,
      "curveFrom": "{0.25940145487806054, 0.21487703296085411}",
      "curveMode": 4,
      "curveTo": "{0.25907945113600589, 0.20744695321893189}",
      "hasCurveFrom": true,
      "hasCurveTo": true,
      "point": "{0.25928737911445582, 0.21366488250440663}"
    },
    {
      "_class": "curvePoint",
      "cornerRadius": 0,
      "curveFrom": "{0.23558358957115733, 0.22803044326740016}",
      "curveMode": 4,
      "curveTo": "{0.25940145487806054, 0.21609772507737549}",
      "hasCurveFrom": true,
      "hasCurveTo": true,
      "point": "{0.25928737911445587, 0.21730987553382297}"
    },
    {
      "_class": "curvePoint",
      "cornerRadius": 0,
      "curveFrom": "{0.17303217584275088, 0.25655173288939154}",
      "curveMode": 4,
      "curveTo": "{0.19857240940705959, 0.24368247215842284}",
      "hasCurveFrom": true,
      "hasCurveTo": true,
      "point": "{0.17923510741121079, 0.25354539447331387}"
    },
    {
      "_class": "curvePoint",
      "cornerRadius": 0,
      "curveFrom": "{0.13866319631859186, 0.28913248859817786}",
      "curveMode": 4,
      "curveTo": "{0.16723156421385504, 0.26037123202135071}",
      "hasCurveFrom": true,
      "hasCurveTo": true,
      "point": "{0.16197708519986181, 0.26490919627090559}"
    },
    {
      "_class": "curvePoint",
      "cornerRadius": 0,
      "curveFrom": "{0.079746420598057075, 0.38397433421866589}",
      "curveMode": 4,
      "curveTo": "{0.12596766715522181, 0.32213207916024966}",
      "hasCurveFrom": true,
      "hasCurveTo": true,
      "point": "{0.12683725684181399, 0.35624843336098322}"
    },
    {
      "_class": "curvePoint",
      "cornerRadius": 0,
      "curveFrom": "{0.0026567343369200604, 0.47743942333416944}",
      "curveMode": 4,
      "curveTo": "{0.039143009342267734, 0.42203748070087038}",
      "hasCurveFrom": true,
      "hasCurveTo": true,
      "point": "{0.0079024531684212806, 0.46774233779018565}"
    },
    {
      "_class": "curvePoint",
      "cornerRadius": 0,
      "curveFrom": "{7.4455786376761889e-05, 0.51788115962157688}",
      "curveMode": 2,
      "curveTo": "{-6.531403269842042e-05, 0.48837165450089065}",
      "hasCurveFrom": true,
      "hasCurveTo": true,
      "point": "{1.1899873217661588e-06, 0.49947521828157421}"
    },
    {
      "_class": "curvePoint",
      "cornerRadius": 0,
      "curveFrom": "{0.031727579647796975, 0.63978166011018023}",
      "curveMode": 4,
      "curveTo": "{0.0025217451485427277, 0.53619527071180373}",
      "hasCurveFrom": true,
      "hasCurveTo": true,
      "point": "{0.0072786692330713137, 0.55393570236814627}"
    },
    {
      "_class": "curvePoint",
      "cornerRadius": 0,
      "curveFrom": "{0.1322433842815138, 0.82902547041173702}",
      "curveMode": 4,
      "curveTo": "{0.06725474767882815, 0.72184968648449965}",
      "hasCurveFrom": true,
      "hasCurveTo": true,
      "point": "{0.112906082285665, 0.79793582398436314}"
    },
    {
      "_class": "curvePoint",
      "cornerRadius": 0,
      "curveFrom": "{0.22107396664626836, 0.98743218255640808}",
      "curveMode": 4,
      "curveTo": "{0.18027474730346088, 0.93301497742743555}",
      "hasCurveFrom": true,
      "hasCurveTo": true,
      "point": "{0.21271151194165891, 0.97461078023371517}"
    },
    {
      "_class": "curvePoint",
      "cornerRadius": 0,
      "curveFrom": "{0.25556580866063133, 1.0003466144018682}",
      "curveMode": 4,
      "curveTo": "{0.23386481962796704, 0.99648091854370069}",
      "hasCurveFrom": true,
      "hasCurveTo": true,
      "point": "{0.24847512423505669, 0.99991132008495742}"
    },
    {
      "_class": "curvePoint",
      "cornerRadius": 0,
      "curveFrom": "{0.28815571301066495, 0.98895831095801934}",
      "curveMode": 3,
      "curveTo": "{0.26266292919392503, 0.99917566800848401}",
      "hasCurveFrom": true,
      "hasCurveTo": true,
      "point": "{0.26926792208005551, 0.99648073841021279}"
    },
    {
      "_class": "curvePoint",
      "cornerRadius": 0,
      "curveFrom": "{0.44496706387029472, 0.89763710390663087}",
      "curveMode": 4,
      "curveTo": "{0.30638178638525188, 0.97977632462133446}",
      "hasCurveFrom": true,
      "hasCurveTo": true,
      "point": "{0.3237450524339523, 0.96903608501225524}"
    },
    {
      "_class": "curvePoint",
      "cornerRadius": 0,
      "curveFrom": "{0.78077074906702415, 0.65813962073851662}",
      "curveMode": 4,
      "curveTo": "{0.69240135822577953, 0.71302892753443181}",
      "hasCurveFrom": true,
      "hasCurveTo": true,
      "point": "{0.74459128081672632, 0.65964050022121745}"
    },
    {
      "_class": "curvePoint",
      "cornerRadius": 0,
      "curveFrom": "{0.92361727026216534, 0.63305349224194596}",
      "curveMode": 3,
      "curveTo": "{0.80925688211467239, 0.65663874125581578}",
      "hasCurveFrom": true,
      "hasCurveTo": true,
      "point": "{0.81965328103717172, 0.65449462770910039}"
    },
    {
      "_class": "curvePoint",
      "cornerRadius": 0,
      "curveFrom": "{1.0117787331249601, 0.36225195129178633}",
      "curveMode": 2,
      "curveTo": "{0.9606284504262631, 0.56444185874705199}",
      "hasCurveFrom": true,
      "hasCurveTo": true,
      "point": "{0.98599566379716153, 0.4660270469528135}"
    }
  ],
  "resizingConstraint": 63,
  "resizingType": 0,
  "rotation": 0,
  "shouldBreakMaskChain": false,
  "style": {
    "_class": "style",
    "blur": {
      "_class": "blur",
      "center": "{0.5, 0.5}",
      "isEnabled": false,
      "motionAngle": 0,
      "radius": 10,
      "saturation": 1,
      "type": 0
    },
    "borderOptions": {
      "_class": "borderOptions",
      "dashPattern": [
      ],
      "isEnabled": true,
      "lineCapStyle": 0,
      "lineJoinStyle": 0
    },
    "borders": [
    ],
    "colorControls": {
      "_class": "colorControls",
      "brightness": 0,
      "contrast": 1,
      "hue": 0,
      "isEnabled": false,
      "saturation": 1
    },
    "contextSettings": {
      "_class": "graphicsContextSettings",
      "blendMode": 0,
      "opacity": 1
    },
    "do_objectID": "B5ACA754-5B54-45B1-AF9D-FEE4C897582F",
    "endMarkerType": 0,
    "fills": [
    ],
    "innerShadows": [
    ],
    "miterLimit": 10,
    "shadows": [
    ],
    "startMarkerType": 0,
    "windingRule": 1
  }
}