{
  "_class": "shapePath",
  "booleanOperation": -1,
  "clippingMaskMode": 0,
  "do_objectID": "FBB70797-E4F7-4B49-8C52-E1AE93CA901F",
  "edited": true,
  "exportOptions": {
    "_class": "exportOptions",
    "exportFormats": [
    ],
    "includedLayerIds": [
    ],
    "layerOptions": 0,
    "shouldTrim": false
  },
  "frame": {
    "_class": "rect",
    "constrainProportions": false,
    "height": 42.67999999999999,
    "width": 40.7939365853699,
    "x": 2.076287940231609,
    "y": 1.99818719828346
  },
  "hasClippingMask": false,
  "isClosed": true,
  "isFixedToViewport": false,
  "isFlippedHorizontal": false,
  "isFlippedVertical": false,
  "isLocked": false,
  "isVisible": true,
  "layerListExpandedType": 0,
  "name": "Path",
  "nameIsFixed": false,
  "pointRadiusBehaviour": 1,
  "points": [
    {
      "_class": "curvePoint",
      "cornerRadius": 0,
      "curveFrom": "{0.99827806142620201, 0.51335520149953151}",
      "curveMode": 4,
      "curveTo": "{0.99974886824266207, 0.50796626054358018}",
      "hasCurveFrom": true,
      "hasCurveTo": false,
      "point": "{0.99974886824266207, 0.50796626054358018}"
    },
    {
      "_class": "curvePoint",
      "cornerRadius": 0,
      "curveFrom": "{0.90978451796919058, 0.52952202436738527}",
      "curveMode": 3,
      "curveTo": "{0.99484617885446192, 0.52600749765698229}",
      "hasCurveFrom": true,
      "hasCurveTo": true,
      "point": "{0.96690084934172138, 0.52717900656044991}"
    },
    {
      "_class": "curvePoint",
      "cornerRadius": 0,
      "curveFrom": "{0.85070711084137951, 0.58364573570759137}",
      "curveMode": 2,
      "curveTo": "{0.87816217141530006, 0.5400656044985942}",
      "hasCurveFrom": true,
      "hasCurveTo": true,
      "point": "{0.86443464112833979, 0.56185567010309279}"
    },
    {
      "_class": "curvePoint",
      "cornerRadius": 0,
      "curveFrom": "{0.87485999504979117, 0.63740855348369874}",
      "curveMode": 4,
      "curveTo": "{0.86198329643423965, 0.61176194939081552}",
      "hasCurveFrom": true,
      "hasCurveTo": true,
      "point": "{0.87129840627181987, 0.63074039362699152}"
    },
    {
      "_class": "curvePoint",
      "cornerRadius": 0,
      "curveFrom": "{0.87506599442314137, 0.65377703253676744}",
      "curveMode": 4,
      "curveTo": "{0.8777334684669954, 0.6443924911059673}",
      "hasCurveFrom": true,
      "hasCurveTo": true,
      "point": "{0.87987811270116989, 0.65159325210871599}"
    },
    {
      "_class": "curvePoint",
      "cornerRadius": 0,
      "curveFrom": "{0.7747154253242784, 0.67174320524835984}",
      "curveMode": 4,
      "curveTo": "{0.8699457607417137, 0.65527679644898229}",
      "hasCurveFrom": true,
      "hasCurveTo": true,
      "point": "{0.86467977559774989, 0.65604498594189309}"
    },
    {
      "_class": "curvePoint",
      "cornerRadius": 0,
      "curveFrom": "{0.76441977760905833, 0.77928772258669154}",
      "curveMode": 4,
      "curveTo": "{0.76662598783374836, 0.70993439550140569}",
      "hasCurveFrom": true,
      "hasCurveTo": true,
      "point": "{0.76441977760905833, 0.74976569821930639}"
    },
    {
      "_class": "curvePoint",
      "cornerRadius": 0,
      "curveFrom": "{0.62297718875948593, 0.83505154639175261}",
      "curveMode": 4,
      "curveTo": "{0.76294897079259827, 0.80037488284910951}",
      "hasCurveFrom": true,
      "hasCurveTo": true,
      "point": "{0.68573161292844709, 0.82005623242736647}"
    },
    {
      "_class": "curvePoint",
      "cornerRadius": 0,
      "curveFrom": "{0.55262359603881495, 0.95196813495782573}",
      "curveMode": 4,
      "curveTo": "{0.55605547861055493, 0.88823805060918448}",
      "hasCurveFrom": false,
      "hasCurveTo": true,
      "point": "{0.55262359603881495, 0.95196813495782573}"
    },
    {
      "_class": "curvePoint",
      "cornerRadius": 0,
      "curveFrom": "{0.52310208020547244, 0.9791904066717636}",
      "curveMode": 4,
      "curveTo": "{0.55262359603881495, 0.99695407685098414}",
      "hasCurveFrom": true,
      "hasCurveTo": false,
      "point": "{0.55262359603881495, 0.99695407685098414}"
    },
    {
      "_class": "curvePoint",
      "cornerRadius": 0,
      "curveFrom": "{0.45702115296891327, 1}",
      "curveMode": 4,
      "curveTo": "{0.4852395164338647, 0.98039671956262464}",
      "hasCurveFrom": false,
      "hasCurveTo": true,
      "point": "{0.45702115296891327, 1}"
    },
    {
      "_class": "curvePoint",
      "cornerRadius": 0,
      "curveFrom": "{0.45358927039717323, 0.88847235238987821}",
      "curveMode": 4,
      "curveTo": "{0.45702115296891327, 0.95079662605435811}",
      "hasCurveFrom": true,
      "hasCurveTo": false,
      "point": "{0.45702115296891327, 0.95079662605435811}"
    },
    {
      "_class": "curvePoint",
      "cornerRadius": 0,
      "curveFrom": "{0.24669577821512992, 0.80154639175257747}",
      "curveMode": 3,
      "curveTo": "{0.38666756024824211, 0.83528584817244622}",
      "hasCurveFrom": true,
      "hasCurveTo": true,
      "point": "{0.32391313607928113, 0.82029053420806008}"
    },
    {
      "_class": "curvePoint",
      "cornerRadius": 0,
      "curveFrom": "{0.24375416458220983, 0.70899718837863179}",
      "curveMode": 3,
      "curveTo": "{0.24596037480689986, 0.78045923149015939}",
      "hasCurveFrom": true,
      "hasCurveTo": true,
      "point": "{0.24497983692925987, 0.75000000000000011}"
    },
    {
      "_class": "curvePoint",
      "cornerRadius": 0,
      "curveFrom": "{0.13968827056919536, 0.65555645405181884}",
      "curveMode": 4,
      "curveTo": "{0.23492932368344971, 0.67080599812558572}",
      "hasCurveFrom": true,
      "hasCurveTo": true,
      "point": "{0.14496497340997824, 0.65627928772258681}"
    },
    {
      "_class": "curvePoint",
      "cornerRadius": 0,
      "curveFrom": "{0.1319112805407327, 0.6446267928866608}",
      "curveMode": 4,
      "curveTo": "{0.13456104493955939, 0.65405464213315545}",
      "hasCurveFrom": true,
      "hasCurveTo": true,
      "point": "{0.12976663630655808, 0.65182755388940949}"
    },
    {
      "_class": "curvePoint",
      "cornerRadius": 0,
      "curveFrom": "{0.14766145257348837, 0.6119962511715088}",
      "curveMode": 4,
      "curveTo": "{0.13478475395793696, 0.63764285526439224}",
      "hasCurveFrom": true,
      "hasCurveTo": true,
      "point": "{0.13834634273590821, 0.63097469540768503}"
    },
    {
      "_class": "curvePoint",
      "cornerRadius": 0,
      "curveFrom": "{0.13001177077596807, 0.53819119025304596}",
      "curveMode": 2,
      "curveTo": "{0.16040844498280851, 0.58598875351452662}",
      "hasCurveFrom": true,
      "hasCurveTo": true,
      "point": "{0.14521010787938829, 0.56208997188378629}"
    },
    {
      "_class": "curvePoint",
      "cornerRadius": 0,
      "curveFrom": "{0.0079348050097860674, 0.52600749765698218}",
      "curveMode": 3,
      "curveTo": "{0.099860231038537556, 0.52975632614807877}",
      "hasCurveFrom": true,
      "hasCurveTo": true,
      "point": "{0.042743899666006634, 0.52741330834114331}"
    },
    {
      "_class": "curvePoint",
      "cornerRadius": 0,
      "curveFrom": "{-0.0062829942159941662, 0.48008434864104965}",
      "curveMode": 4,
      "curveTo": "{0.0032772500909960035, 0.51077788191190243}",
      "hasCurveFrom": true,
      "hasCurveTo": true,
      "point": "{0.0015613088051259685, 0.50562324273664472}"
    },
    {
      "_class": "curvePoint",
      "cornerRadius": 0,
      "curveFrom": "{0.10402751701850767, 0.37160262417994366}",
      "curveMode": 2,
      "curveTo": "{0.015779108030906201, 0.43064667291471415}",
      "hasCurveFrom": true,
      "hasCurveTo": true,
      "point": "{0.059903312524706938, 0.40112464854732888}"
    },
    {
      "_class": "curvePoint",
      "cornerRadius": 0,
      "curveFrom": "{0.061761802471297048, 0.29777949455967712}",
      "curveMode": 4,
      "curveTo": "{0.076817590913997202, 0.32263355201499522}",
      "hasCurveFrom": true,
      "hasCurveTo": true,
      "point": "{0.064560867443496997, 0.30224929709465786}"
    },
    {
      "_class": "curvePoint",
      "cornerRadius": 0,
      "curveFrom": "{0.053774950789456794, 0.27858481724461093}",
      "curveMode": 4,
      "curveTo": "{0.059224833362569576, 0.2931644414566994}",
      "hasCurveFrom": true,
      "hasCurveTo": true,
      "point": "{0.056961698891786865, 0.28842549203373941}"
    },
    {
      "_class": "curvePoint",
      "cornerRadius": 0,
      "curveFrom": "{0.090617908910430769, 0.24893868838559557}",
      "curveMode": 4,
      "curveTo": "{0.051813875034176761, 0.2727272727272726}",
      "hasCurveFrom": true,
      "hasCurveTo": true,
      "point": "{0.081475145832787269, 0.25421743205248348}"
    },
    {
      "_class": "curvePoint",
      "cornerRadius": 0,
      "curveFrom": "{0.1206308915871331, 0.24023696633687797}",
      "curveMode": 2,
      "curveTo": "{0.10053196331662539, 0.24499037822128944}",
      "hasCurveFrom": true,
      "hasCurveTo": true,
      "point": "{0.11089128216198772, 0.24250234301780685}"
    },
    {
      "_class": "curvePoint",
      "cornerRadius": 0,
      "curveFrom": "{0.16307095874421099, 0.21560738442531019}",
      "curveMode": 4,
      "curveTo": "{0.12996562813143581, 0.23660490930638287}",
      "hasCurveFrom": true,
      "hasCurveTo": true,
      "point": "{0.13859147720531811, 0.23172446110590419}"
    },
    {
      "_class": "curvePoint",
      "cornerRadius": 0,
      "curveFrom": "{0.17364570633094872, 0.13636363636363638}",
      "curveMode": 4,
      "curveTo": "{0.17648837161146513, 0.18807509493293045}",
      "hasCurveFrom": true,
      "hasCurveTo": true,
      "point": "{0.17364570633094872, 0.15979381443298973}"
    },
    {
      "_class": "curvePoint",
      "cornerRadius": 0,
      "curveFrom": "{0.26042330850209011, 0.1187910028116214}",
      "curveMode": 3,
      "curveTo": "{0.17487137867799876, 0.13027179006560452}",
      "hasCurveFrom": true,
      "hasCurveTo": true,
      "point": "{0.20796453204834925, 0.12582005623242742}"
    },
    {
      "_class": "curvePoint",
      "cornerRadius": 0,
      "curveFrom": "{0.27586678007492044, 0.053655107778819149}",
      "curveMode": 3,
      "curveTo": "{0.26924814940085023, 0.09231490159325216}",
      "hasCurveFrom": true,
      "hasCurveTo": true,
      "point": "{0.27341543538082036, 0.067947516401124675}"
    },
    {
      "_class": "curvePoint",
      "cornerRadius": 0,
      "curveFrom": "{0.33386578137408773, 0.040186450757439346}",
      "curveMode": 4,
      "curveTo": "{0.2768473179525604, 0.047094657919400193}",
      "hasCurveFrom": true,
      "hasCurveTo": true,
      "point": "{0.313617488364061, 0.043345829428303652}"
    },
    {
      "_class": "curvePoint",
      "cornerRadius": 0,
      "curveFrom": "{0.38241227792281579, 0.061109481454775932}",
      "curveMode": 4,
      "curveTo": "{0.35462984825860883, 0.04400627653848882}",
      "hasCurveFrom": true,
      "hasCurveTo": true,
      "point": "{0.37220462655305198, 0.05412371134020625}"
    },
    {
      "_class": "curvePoint",
      "cornerRadius": 0,
      "curveFrom": "{0.42103465723015898, 0.055900275060242706}",
      "curveMode": 4,
      "curveTo": "{0.3952269255667577, 0.063661222723865818}",
      "hasCurveFrom": true,
      "hasCurveTo": true,
      "point": "{0.40750399014809252, 0.061152764761012265}"
    },
    {
      "_class": "curvePoint",
      "cornerRadius": 0,
      "curveFrom": "{0.45334193091794295, 0.013085421515672454}",
      "curveMode": 4,
      "curveTo": "{0.43180388704623612, 0.045691317691446097}",
      "hasCurveFrom": true,
      "hasCurveTo": true,
      "point": "{0.43741039541611293, 0.032802249297094715}"
    },
    {
      "_class": "curvePoint",
      "cornerRadius": 0,
      "curveFrom": "{0.52963625821459004, 0.0010842453771553371}",
      "curveMode": 4,
      "curveTo": "{0.4775571460990381, 0.0010842453771553787}",
      "hasCurveFrom": true,
      "hasCurveTo": true,
      "point": "{0.50359670215681407, 0}"
    },
    {
      "_class": "curvePoint",
      "cornerRadius": 0,
      "curveFrom": "{0.57524594134240803, 0.045782977380406972}",
      "curveMode": 4,
      "curveTo": "{0.5538514733956853, 0.013085421515672413}",
      "hasCurveFrom": true,
      "hasCurveTo": true,
      "point": "{0.56978300889751521, 0.032802249297094674}"
    },
    {
      "_class": "curvePoint",
      "cornerRadius": 0,
      "curveFrom": "{0.61196654057679434, 0.063631643689457465}",
      "curveMode": 4,
      "curveTo": "{0.58606403453105294, 0.05603825598999413}",
      "hasCurveFrom": true,
      "hasCurveTo": true,
      "point": "{0.59968941416553567, 0.061152764761012141}"
    },
    {
      "_class": "curvePoint",
      "cornerRadius": 0,
      "curveFrom": "{0.65246956463596351, 0.043763007965708693}",
      "curveMode": 4,
      "curveTo": "{0.62476871166594672, 0.061082386838249077}",
      "hasCurveFrom": true,
      "hasCurveTo": true,
      "point": "{0.63498877776057627, 0.054123711340206042}"
    },
    {
      "_class": "curvePoint",
      "cornerRadius": 0,
      "curveFrom": "{0.73034608636106779, 0.046391752577319562}",
      "curveMode": 4,
      "curveTo": "{0.67323996349018234, 0.039692822293617515}",
      "hasCurveFrom": true,
      "hasCurveTo": true,
      "point": "{0.69357591594956725, 0.042642924086223027}"
    },
    {
      "_class": "curvePoint",
      "cornerRadius": 0,
      "curveFrom": "{0.73794525491277796, 0.090674789128397368}",
      "curveMode": 2,
      "curveTo": "{0.73132662423870776, 0.052952202436738482}",
      "hasCurveFrom": true,
      "hasCurveTo": true,
      "point": "{0.73377796893280789, 0.067244611059044043}"
    },
    {
      "_class": "curvePoint",
      "cornerRadius": 0,
      "curveFrom": "{0.83232202563562951, 0.1295688847235239}",
      "curveMode": 3,
      "curveTo": "{0.74677009581153808, 0.11808809746954077}",
      "hasCurveFrom": true,
      "hasCurveTo": true,
      "point": "{0.79922887226527894, 0.12511715089034678}"
    },
    {
      "_class": "curvePoint",
      "cornerRadius": 0,
      "curveFrom": "{0.83070939534974586, 0.18726563721408568}",
      "curveMode": 4,
      "curveTo": "{0.83256716010503951, 0.13589503280224935}",
      "hasCurveFrom": true,
      "hasCurveTo": true,
      "point": "{0.83330256351326959, 0.15909090909090912}"
    },
    {
      "_class": "curvePoint",
      "cornerRadius": 0,
      "curveFrom": "{0.87706843196347439, 0.2356704781626312}",
      "curveMode": 4,
      "curveTo": "{0.84408080108301053, 0.21461414668237691}",
      "hasCurveFrom": true,
      "hasCurveTo": true,
      "point": "{0.86835679263890009, 0.23078725398313019}"
    },
    {
      "_class": "curvePoint",
      "cornerRadius": 0,
      "curveFrom": "{0.90666144099700308, 0.24405317109851532}",
      "curveMode": 2,
      "curveTo": "{0.88648437646450595, 0.23930199511700737}",
      "hasCurveFrom": true,
      "hasCurveTo": true,
      "point": "{0.89630212215164062, 0.24156513589503273}"
    },
    {
      "_class": "curvePoint",
      "cornerRadius": 0,
      "curveFrom": "{0.95636006715709165, 0.27179006560449853}",
      "curveMode": 4,
      "curveTo": "{0.91657549540319783, 0.24800148126282154}",
      "hasCurveFrom": true,
      "hasCurveTo": true,
      "point": "{0.92571825848084111, 0.25328022492970942}"
    },
    {
      "_class": "curvePoint",
      "cornerRadius": 0,
      "curveFrom": "{0.9479256408575677, 0.29232581877953207}",
      "curveMode": 4,
      "curveTo": "{0.9546441258712216, 0.27671040299906274}",
      "hasCurveFrom": true,
      "hasCurveTo": true,
      "point": "{0.95023170542184154, 0.28748828491096529}"
    },
    {
      "_class": "curvePoint",
      "cornerRadius": 0,
      "curveFrom": "{0.92964040999140096, 0.322867853795689}",
      "curveMode": 4,
      "curveTo": "{0.94530577501403057, 0.29702099103893803}",
      "hasCurveFrom": true,
      "hasCurveTo": true,
      "point": "{0.94238740240072116, 0.30154639175257747}"
    },
    {
      "_class": "curvePoint",
      "cornerRadius": 0,
      "curveFrom": "{0.97670622811812169, 0.41752577319587636}",
      "curveMode": 4,
      "curveTo": "{0.8999791391927906, 0.3718369259606375}",
      "hasCurveFrom": true,
      "hasCurveTo": true,
      "point": "{0.94851576413597127, 0.40112464854732915}"
    },
    {
      "_class": "curvePoint",
      "cornerRadius": 0,
      "curveFrom": "{0.99852319589561211, 0.50796626054358018}",
      "curveMode": 4,
      "curveTo": "{1.0071029023249622, 0.47610121836925967}",
      "hasCurveFrom": false,
      "hasCurveTo": true,
      "point": "{0.99852319589561211, 0.50796626054358018}"
    }
  ],
  "resizingConstraint": 63,
  "resizingType": 0,
  "rotation": 0,
  "shouldBreakMaskChain": false,
  "style": {
    "_class": "style",
    "blur": {
      "_class": "blur",
      "center": "{0.5, 0.5}",
      "isEnabled": false,
      "motionAngle": 0,
      "radius": 10,
      "saturation": 1,
      "type": 0
    },
    "borderOptions": {
      "_class": "borderOptions",
      "dashPattern": [
      ],
      "isEnabled": true,
      "lineCapStyle": 0,
      "lineJoinStyle": 0
    },
    "borders": [
    ],
    "colorControls": {
      "_class": "colorControls",
      "brightness": 0,
      "contrast": 1,
      "hue": 0,
      "isEnabled": false,
      "saturation": 1
    },
    "contextSettings": {
      "_class": "graphicsContextSettings",
      "blendMode": 0,
      "opacity": 1
    },
    "do_objectID": "32D1AB60-32A6-4EED-B36C-1A165CC2B975",
    "endMarkerType": 0,
    "fills": [
    ],
    "innerShadows": [
    ],
    "miterLimit": 10,
    "shadows": [
    ],
    "startMarkerType": 0,
    "windingRule": 1
  }
}